nifpy/__init__.py
nifpy/constants.py
nifpy/financials.py
nifpy/graph.py
nifpy/indexes.py
nifpy/info.py
nifpy/utils.py
nifpy-3.0.1.dist-info/licenses/LICENSE
nifpy-3.0.1.dist-info/METADATA
nifpy-3.0.1.dist-info/WHEEL
nifpy-3.0.1.dist-info/top_level.txt
nifpy-3.0.1.dist-info/RECORD
