Metadata-Version: 2.4
Name: nifpy
Version: 3.0.1
Summary: Easy to use python package that can be used to fetch live price, closing price, stock summary, 
Home-page: https://github.com/shresth26/nifpy
Author: Shresth Singh
Author-email: singhshresth26@gmail.com
License: MIT
Keywords: stocks,nifty,financials,algo trading,nse,crypto,cryptocurrency,sensex
License-File: LICENSE
Dynamic: author
Dynamic: author-email
Dynamic: description
Dynamic: description-content-type
Dynamic: home-page
Dynamic: keywords
Dynamic: license
Dynamic: license-file
Dynamic: summary
